asar/__init__.py
asar/asar.py
asar/integrity.py
asar/limited_reader.py
asar/metadata.py
asar-0.1.1.dist-info/LICENSE
asar-0.1.1.dist-info/METADATA
asar-0.1.1.dist-info/WHEEL
asar-0.1.1.dist-info/top_level.txt
asar-0.1.1.dist-info/RECORD
