Metadata-Version: 2.1
Name: asar
Version: 0.1.1
Summary: Library for working with Electron's ASAR archive files
Author-email: Black <hello.bug@foxmail.com>
Project-URL: Homepage, https://github.com/black-06/asar-py
Keywords: asar
Classifier: Programming Language :: Python :: 3
License-File: LICENSE
